acts_channel-0.4.0.dist-info/METADATA
acts_channel-0.4.0.dist-info/WHEEL
acts_channel-0.4.0.dist-info/entry_points.txt
acts_channel-0.4.0.dist-info/licenses/LICENSE
acts_channel/__init__.py
acts_channel/channel.py
acts_channel/proto/__init__.py
acts_channel/proto/acts_pb2.py
acts_channel/proto/acts_pb2_grpc.py
acts_channel-0.4.0.dist-info/RECORD
