Metadata-Version: 2.1
Name: acts-channel
Version: 0.4.0
Summary: acts channel client
Keywords: workflow,acts-channel
Author-Email: yaojianping <yaojianpin@sohu.com>
License: MIT
Requires-Python: >=3.8
Requires-Dist: nanoid>=2.0.0
Requires-Dist: result>=0.17.0
